setup.py
pylicense/__init__.py
pylicense/pylicense.py
pylicense.egg-info/PKG-INFO
pylicense.egg-info/SOURCES.txt
pylicense.egg-info/dependency_links.txt
pylicense.egg-info/entry_points.txt
pylicense.egg-info/requires.txt
pylicense.egg-info/top_level.txt