Metadata-Version: 1.0
Name: pylicense
Version: 1
Summary: License extractor from the python eggs.
Home-page: https://github.com/livenson/pylicense
Author: Ilja Livenson
Author-email: ilja.livenson@gmail.com
License: BSD
Platform: UNKNOWN
